flazzy/api.py
flazzy/cli.py
flazzy/config.py
flazzy/converter.py
flazzy/plot.py
flazzy/utils.py
flazzy-0.2.7.dist-info/LICENSE
flazzy-0.2.7.dist-info/METADATA
flazzy-0.2.7.dist-info/WHEEL
flazzy-0.2.7.dist-info/entry_points.txt
flazzy-0.2.7.dist-info/RECORD
