Metadata-Version: 2.3
Name: flazzy
Version: 0.2.7
Summary: A command-line tool to check and convert currency rates.
License: LGPL-2.1-or-later
Author: surya
Author-email: surya.a@tutamail.com
Requires-Python: >=3.12
Classifier: Programming Language :: Python :: 3
Classifier: Operating System :: OS Independent
Classifier: License :: OSI Approved :: GNU Lesser General Public License v3 or later (LGPLv3+)
Classifier: Topic :: Utilities
Classifier: Environment :: Console
Requires-Dist: click (>=8.2.1,<9.0.0)
Requires-Dist: matplotlib (>=3.10.3,<4.0.0)
Requires-Dist: pytest-sugar (>=1.0.0,<2.0.0)
Requires-Dist: requests (>=2.32.4,<3.0.0)
Requires-Dist: rich (>=14.0.0,<15.0.0)
Requires-Dist: rich-click (>=1.8.9,<2.0.0)
